{
  "input": null,
  "inputs": [
    "hub_nasdaq100_1y_1d\\AAPL_1y_1d.csv",
    "hub_nasdaq100_1y_1d\\ABNB_1y_1d.csv",
    "hub_nasdaq100_1y_1d\\ADBE_1y_1d.csv",
    "hub_nasdaq100_1y_1d\\ADI_1y_1d.csv",
    "hub_nasdaq100_1y_1d\\ADP_1y_1d.csv",
    "hub_nasdaq100_1y_1d\\ADSK_1y_1d.csv",
    "hub_nasdaq100_1y_1d\\AEP_1y_1d.csv",
    "hub_nasdaq100_1y_1d\\ALNY_1y_1d.csv",
    "hub_nasdaq100_1y_1d\\AMAT_1y_1d.csv",
    "hub_nasdaq100_1y_1d\\AMD_1y_1d.csv",
    "hub_nasdaq100_1y_1d\\AMGN_1y_1d.csv",
    "hub_nasdaq100_1y_1d\\AMZN_1y_1d.csv",
    "hub_nasdaq100_1y_1d\\APP_1y_1d.csv",
    "hub_nasdaq100_1y_1d\\ARM_1y_1d.csv",
    "hub_nasdaq100_1y_1d\\ASML_1y_1d.csv",
    "hub_nasdaq100_1y_1d\\AVGO_1y_1d.csv",
    "hub_nasdaq100_1y_1d\\AXON_1y_1d.csv",
    "hub_nasdaq100_1y_1d\\AZN_1y_1d.csv",
    "hub_nasdaq100_1y_1d\\BKNG_1y_1d.csv",
    "hub_nasdaq100_1y_1d\\BKR_1y_1d.csv",
    "hub_nasdaq100_1y_1d\\CCEP_1y_1d.csv",
    "hub_nasdaq100_1y_1d\\CDNS_1y_1d.csv",
    "hub_nasdaq100_1y_1d\\CEG_1y_1d.csv",
    "hub_nasdaq100_1y_1d\\CHTR_1y_1d.csv",
    "hub_nasdaq100_1y_1d\\CMCSA_1y_1d.csv",
    "hub_nasdaq100_1y_1d\\COST_1y_1d.csv",
    "hub_nasdaq100_1y_1d\\CPRT_1y_1d.csv",
    "hub_nasdaq100_1y_1d\\CRWD_1y_1d.csv",
    "hub_nasdaq100_1y_1d\\CSCO_1y_1d.csv",
    "hub_nasdaq100_1y_1d\\CSGP_1y_1d.csv",
    "hub_nasdaq100_1y_1d\\CSX_1y_1d.csv",
    "hub_nasdaq100_1y_1d\\CTAS_1y_1d.csv",
    "hub_nasdaq100_1y_1d\\CTSH_1y_1d.csv",
    "hub_nasdaq100_1y_1d\\DASH_1y_1d.csv",
    "hub_nasdaq100_1y_1d\\DDOG_1y_1d.csv",
    "hub_nasdaq100_1y_1d\\DXCM_1y_1d.csv",
    "hub_nasdaq100_1y_1d\\EA_1y_1d.csv",
    "hub_nasdaq100_1y_1d\\EXC_1y_1d.csv",
    "hub_nasdaq100_1y_1d\\FANG_1y_1d.csv",
    "hub_nasdaq100_1y_1d\\FAST_1y_1d.csv",
    "hub_nasdaq100_1y_1d\\FER_1y_1d.csv",
    "hub_nasdaq100_1y_1d\\FTNT_1y_1d.csv",
    "hub_nasdaq100_1y_1d\\GEHC_1y_1d.csv",
    "hub_nasdaq100_1y_1d\\GILD_1y_1d.csv",
    "hub_nasdaq100_1y_1d\\GOOG_1y_1d.csv",
    "hub_nasdaq100_1y_1d\\GOOGL_1y_1d.csv",
    "hub_nasdaq100_1y_1d\\HON_1y_1d.csv",
    "hub_nasdaq100_1y_1d\\IDXX_1y_1d.csv",
    "hub_nasdaq100_1y_1d\\INSM_1y_1d.csv",
    "hub_nasdaq100_1y_1d\\TEAM_1y_1d.csv"
  ],
  "feature_count": 85,
  "mode": "walkforward",
  "task": "classification",
  "model": "hgb",
  "n_folds": 5,
  "purge": 5,
  "test_window": 20,
  "cv_metrics_csv": "hub_nasdaq100_1y_1d_ml\\cv_metrics.csv",
  "n_assets": 50,
  "assets": [
    "AAPL",
    "ABNB",
    "ADBE",
    "ADI",
    "ADP",
    "ADSK",
    "AEP",
    "ALNY",
    "AMAT",
    "AMD",
    "AMGN",
    "AMZN",
    "APP",
    "ARM",
    "ASML",
    "AVGO",
    "AXON",
    "AZN",
    "BKNG",
    "BKR",
    "CCEP",
    "CDNS",
    "CEG",
    "CHTR",
    "CMCSA",
    "COST",
    "CPRT",
    "CRWD",
    "CSCO",
    "CSGP",
    "CSX",
    "CTAS",
    "CTSH",
    "DASH",
    "DDOG",
    "DXCM",
    "EA",
    "EXC",
    "FANG",
    "FAST",
    "FER",
    "FTNT",
    "GEHC",
    "GILD",
    "GOOG",
    "GOOGL",
    "HON",
    "IDXX",
    "INSM",
    "TEAM"
  ]
}