{
  "asset": "EURUSD=X",
  "input": "smoke_market_fx_1mo_1d\\EURUSD=X_1mo_1d.csv",
  "variant": "mlp_baseline",
  "model": "mlp",
  "mode": "long_short",
  "task": "classification",
  "signal_source": "predict",
  "proba_enter": 0.55,
  "cost_bps": 5.0,
  "slippage_bps": 0.0,
  "execution_delay": 1,
  "vol_target": null,
  "stop_loss": null,
  "take_profit": null,
  "trailing_atr_mult": null,
  "uses_hmm": false,
  "uses_fft": false,
  "uses_dmd": false,
  "uses_neural_net": true,
  "metrics": {
    "start": "2025-12-17 00:00:00",
    "end": "2026-01-08 00:00:00",
    "n_bars": 16,
    "total_return": 0.006967854379785088,
    "cagr": 0.1221887874913632,
    "max_drawdown": -0.0004829730719132508,
    "ann_factor": 265.6363636363636,
    "sharpe": 7.733572889338035,
    "avg_bar_return": 0.0004344935573264326,
    "vol_bar": 0.000915686731471957,
    "turnover_sum": 1.0,
    "n_position_changes": 1
  },
  "trade_metrics": {
    "n_trades": 0,
    "n_wins": 0,
    "n_losses": 0,
    "n_breakeven": 0,
    "win_rate": NaN,
    "win_loss_ratio": NaN,
    "avg_win": NaN,
    "avg_loss": NaN,
    "profit_factor": NaN,
    "expectancy": NaN
  }
}