{
  "asset": "EURUSD=X",
  "input": "outputs_eurusd_5y_1d\\EURUSD=X_5y_1d.csv",
  "variant": "rf_stops",
  "model": "rf",
  "mode": "long_short",
  "task": "classification",
  "signal_source": "predict",
  "proba_enter": 0.55,
  "cost_bps": 5.0,
  "slippage_bps": 0.0,
  "execution_delay": 1,
  "vol_target": null,
  "stop_loss": 0.01,
  "take_profit": 0.02,
  "trailing_atr_mult": null,
  "uses_hmm": false,
  "uses_fft": false,
  "uses_dmd": false,
  "uses_neural_net": false,
  "metrics": {
    "start": "2021-01-25 00:00:00",
    "end": "2026-01-13 00:00:00",
    "n_bars": 1286,
    "total_return": 0.00943607969611504,
    "cagr": 0.0018928414415295691,
    "max_drawdown": -0.08817711223739055,
    "ann_factor": 258.93687982359427,
    "sharpe": 0.06620650411034207,
    "avg_bar_return": 1.0661863545948487e-05,
    "vol_bar": 0.002591369952368969,
    "turnover_sum": 129.0,
    "n_position_changes": 99
  },
  "trade_metrics": {
    "n_trades": 64,
    "n_wins": 32,
    "n_losses": 32,
    "n_breakeven": 0,
    "win_rate": 0.5,
    "win_loss_ratio": 1.0,
    "avg_win": 0.010544045663972518,
    "avg_loss": -0.008363694231252543,
    "profit_factor": 1.2606923893239275,
    "expectancy": 0.0010901757163599875,
    "median_trade_return": 0.0005496116716544597,
    "exit_reason_counts": {
      "signal": 30,
      "stop_loss": 25,
      "take_profit": 9
    }
  }
}